{
  "$schema": "https://opencode.ai/desktop-theme.json",
  "name": "GitHub Dark Colorblind",
  "id": "github-dark-colorblind",
  "light": {
    "seeds": {
      "neutral": "#6e7781",
      "primary": "#0969da",
      "success": "#1a7f37",
      "warning": "#9a6700",
      "error": "#cf222e",
      "info": "#0969da",
      "interactive": "#0969da",
      "diffAdd": "#1f6feb",
      "diffDelete": "#bc4c00"
    },
    "overrides": {
      "background-base": "#ffffff",
      "background-weak": "#f6f8fa",
      "background-strong": "#f6f8fa",
      "background-stronger": "#ffffff",
      "surface-base": "#f6f8fa",
      "surface-diff-add-base": "#ddf4ff",
      "surface-diff-delete-base": "#fff1e5",
      "surface-diff-hidden-base": "#ede9fe",
      "border-weak-base": "#d8dee4",
      "border-base": "#d0d7de",
      "border-strong-base": "#8c959f",
      "text-base": "#24292f",
      "text-weak": "#57606a",
      "text-strong": "#1f2328",
      "text-interactive-base": "#0969da",
      "icon-base": "#57606a",
      "icon-strong-base": "#24292f",
      "syntax-string": "#0a7f42",
      "syntax-primitive": "#cf222e",
      "syntax-property": "#0550ae",
      "syntax-type": "#9a6700",
      "syntax-constant": "#0550ae",
      "syntax-info": "#0550ae",
      "markdown-heading": "#0550ae",
      "markdown-text": "#24292f",
      "markdown-link": "#0550ae",
      "markdown-link-text": "#0550ae",
      "markdown-code": "#0a7f42",
      "markdown-block-quote": "#9a6700",
      "markdown-emph": "#9a6700",
      "markdown-strong": "#cf222e",
      "markdown-horizontal-rule": "#d8dee4",
      "markdown-list-item": "#0550ae",
      "markdown-list-enumeration": "#0550ae",
      "markdown-image": "#0550ae",
      "markdown-image-text": "#0550ae",
      "markdown-code-block": "#24292f"
    }
  },
  "dark": {
    "seeds": {
      "neutral": "#8b949e",
      "primary": "#58a6ff",
      "success": "#3fb950",
      "warning": "#d29922",
      "error": "#f85149",
      "info": "#79c0ff",
      "interactive": "#58a6ff",
      "diffAdd": "#388bfd",
      "diffDelete": "#db6d28"
    },
    "overrides": {
      "background-base": "#0d1117",
      "background-weak": "#161b22",
      "background-strong": "#161b22",
      "background-stronger": "#0d1117",
      "surface-base": "#161b22",
      "surface-diff-add-base": "#0d2748",
      "surface-diff-delete-base": "#3a2312",
      "surface-diff-hidden-base": "#2a1f5a",
      "border-weak-base": "#30363d",
      "border-base": "#30363d",
      "border-strong-base": "#6e7681",
      "text-base": "#c9d1d9",
      "text-weak": "#8b949e",
      "text-strong": "#f0f6fc",
      "text-interactive-base": "#58a6ff",
      "icon-base": "#8b949e",
      "icon-strong-base": "#f0f6fc",
      "syntax-string": "#56d364",
      "syntax-primitive": "#ff7b72",
      "syntax-property": "#79c0ff",
      "syntax-type": "#d2a8ff",
      "syntax-constant": "#79c0ff",
      "syntax-info": "#79c0ff",
      "markdown-heading": "#79c0ff",
      "markdown-text": "#c9d1d9",
      "markdown-link": "#58a6ff",
      "markdown-link-text": "#79c0ff",
      "markdown-code": "#56d364",
      "markdown-block-quote": "#d29922",
      "markdown-emph": "#d29922",
      "markdown-strong": "#ff7b72",
      "markdown-horizontal-rule": "#30363d",
      "markdown-list-item": "#58a6ff",
      "markdown-list-enumeration": "#79c0ff",
      "markdown-image": "#58a6ff",
      "markdown-image-text": "#79c0ff",
      "markdown-code-block": "#c9d1d9"
    }
  }
}
